{
  "name": "Resident",
  "fields": [
    {
      "fieldName": "firstName",
      "fieldType": "String",
      "fieldValidateRules": [
        "required"
      ]
    },
    {
      "fieldName": "lastName",
      "fieldType": "String",
      "fieldValidateRules": [
        "required"
      ]
    },
    {
      "fieldName": "idNumber",
      "fieldType": "Integer",
      "fieldValidateRules": [
        "required"
      ]
    }
  ],
  "relationships": [
    {
      "relationshipType": "many-to-one",
      "otherEntityName": "facility",
      "otherEntityRelationshipName": "resident",
      "relationshipName": "facility",
      "otherEntityField": "id"
    }
  ],
  "changelogDate": "20201213205509",
  "entityTableName": "resident",
  "dto": "no",
  "pagination": "no",
  "service": "no",
  "jpaMetamodelFiltering": false,
  "fluentMethods": true,
  "readOnly": false,
  "embedded": false,
  "clientRootFolder": "",
  "applications": "*"
}
